autotime/__init__.py
autotime/__version__.py
autotime/models/__init__.py
autotime/models/dl.py
autotime/models/ml.py
autotime/models/prophet.py
autotime/models/pyflux.py
autotime/models/ar_based/__init__.py
autotime/models/ar_based/arima.py
autotime/models/ar_based/param_finder.py
autotime/models/ar_based/sarimax.py
autotime/models/ar_based/var.py
autotime/utils/__init__.py
autotime/utils/classes.py
autotime/utils/eda.py
autotime/utils/etl.py
autotime/utils/metrics.py
autotime/utils/val.py
autotime-0.1.5.dist-info/LICENSE
autotime-0.1.5.dist-info/METADATA
autotime-0.1.5.dist-info/WHEEL
autotime-0.1.5.dist-info/top_level.txt
autotime-0.1.5.dist-info/RECORD
